{
    "name": "level-as-443",
    "version": 18,
    "revisions": [
        {
            "revision": 4,
            "global_revision": 1517786534,
            "author": 8752576,
            "stamp": 1706494494,
            "flags": "S",
            "commentary": ""
        },
        {
            "revision": 3,
            "global_revision": 1517731287,
            "author": 8752576,
            "stamp": 1706313421,
            "flags": "A",
            "commentary": "已新增标签：封闭性, 生存难度1。 移除标签：生存难度1封闭性。"
        },
        {
            "revision": 2,
            "global_revision": 1517731284,
            "author": 8752576,
            "stamp": 1706313407,
            "flags": "A",
            "commentary": "已新增标签：生存难度1封闭性。 移除标签：生存难度1。"
        },
        {
            "revision": 1,
            "global_revision": 1517731279,
            "author": 8752576,
            "stamp": 1706313386,
            "flags": "A",
            "commentary": "已新增标签：原创, 层级, 生存难度1。"
        },
        {
            "revision": 0,
            "global_revision": 1517722231,
            "author": 8752576,
            "stamp": 1706278044,
            "flags": "N",
            "commentary": ""
        }
    ],
    "files": [],
    "page_id": 1452351375,
    "rating": 9,
    "tags": [
        "原创",
        "封闭性",
        "层级",
        "生存难度1"
    ],
    "title": "Level AS-443",
    "sitemap_update": 1706494494000,
    "votings": [
        [
            8113340,
            true
        ],
        [
            8827633,
            true
        ],
        [
            9112210,
            true
        ],
        [
            8752576,
            true
        ],
        [
            9018165,
            true
        ],
        [
            10451005,
            true
        ],
        [
            8747271,
            true
        ],
        [
            9168168,
            true
        ],
        [
            8666147,
            true
        ]
    ],
    "is_locked": false
}